<?xml version="1.0" encoding="utf-8" ?>
<dwsync>
<file name="header.png" server="C:/Users/澤田/Documents/澤田作業データ/htmlデータ/HG_住宅ローン/" local="130138415110000000" remote="130138415110000000" />
<file name="hikaku_ttl01.png" server="C:/Users/澤田/Documents/澤田作業データ/htmlデータ/HG_住宅ローン/" local="130138415110000000" remote="130138415110000000" />
<file name="li.gif" server="C:/Users/澤田/Documents/澤田作業データ/htmlデータ/HG_住宅ローン/" local="130138415110000000" remote="130138415110000000" />
<file name="logo.png" server="C:/Users/澤田/Documents/澤田作業データ/htmlデータ/HG_住宅ローン/" local="130138415110000000" remote="130138415110000000" />
<file name="navi.gif" server="C:/Users/澤田/Documents/澤田作業データ/htmlデータ/HG_住宅ローン/" local="130138415110000000" remote="130138415110000000" />
<file name="navi_li.gif" server="C:/Users/澤田/Documents/澤田作業データ/htmlデータ/HG_住宅ローン/" local="130138415110000000" remote="130138415110000000" />
<file name="navi_li_ov.gif" server="C:/Users/澤田/Documents/澤田作業データ/htmlデータ/HG_住宅ローン/" local="130138415110000000" remote="130138415110000000" />
<file name="side_ico01.png" server="C:/Users/澤田/Documents/澤田作業データ/htmlデータ/HG_住宅ローン/" local="130138415100000000" remote="130138415100000000" />
<file name="side_ico02.png" server="C:/Users/澤田/Documents/澤田作業データ/htmlデータ/HG_住宅ローン/" local="130138415100000000" remote="130138415100000000" />
<file name="side_ico03.png" server="C:/Users/澤田/Documents/澤田作業データ/htmlデータ/HG_住宅ローン/" local="130138415100000000" remote="130138415100000000" />
<file name="side_ico04.png" server="C:/Users/澤田/Documents/澤田作業データ/htmlデータ/HG_住宅ローン/" local="130138415100000000" remote="130138415100000000" />
<file name="side_ico05.png" server="C:/Users/澤田/Documents/澤田作業データ/htmlデータ/HG_住宅ローン/" local="130138415100000000" remote="130138415100000000" />
<file name="side_li.gif" server="C:/Users/澤田/Documents/澤田作業データ/htmlデータ/HG_住宅ローン/" local="130138415110000000" remote="130138415110000000" />
<file name="side_li_ov.gif" server="C:/Users/澤田/Documents/澤田作業データ/htmlデータ/HG_住宅ローン/" local="130138415110000000" remote="130138415110000000" />
<file name="side_mida01.png" server="C:/Users/澤田/Documents/澤田作業データ/htmlデータ/HG_住宅ローン/" local="130138415110000000" remote="130138415110000000" />
<file name="side_mida02.png" server="C:/Users/澤田/Documents/澤田作業データ/htmlデータ/HG_住宅ローン/" local="130138415110000000" remote="130138415110000000" />
<file name="side_ttl01.png" server="C:/Users/澤田/Documents/澤田作業データ/htmlデータ/HG_住宅ローン/" local="130138415110000000" remote="130138415110000000" />
<file name="side_ttl02.png" server="C:/Users/澤田/Documents/澤田作業データ/htmlデータ/HG_住宅ローン/" local="130138415110000000" remote="130138415110000000" />
<file name="top_ttl01.png" server="C:/Users/澤田/Documents/澤田作業データ/htmlデータ/HG_住宅ローン/" local="130138415110000000" remote="130138415110000000" />
</dwsync>